easy2fa/__init__.py
easy2fa/tests/__init__.py
easy2fa/tests/test_argparser.py
easy2fa/tests/test_checkinput.py
easy2fa-0.8.dist-info/DESCRIPTION.rst
easy2fa-0.8.dist-info/METADATA
easy2fa-0.8.dist-info/RECORD
easy2fa-0.8.dist-info/WHEEL
easy2fa-0.8.dist-info/entry_points.txt
easy2fa-0.8.dist-info/metadata.json
easy2fa-0.8.dist-info/top_level.txt
