Metadata-Version: 2.0
Name: easy2fa
Version: 0.8
Summary: Easy to use two-factor-auth client for cli
Home-page: https://github.com/lutostag/easy2fa
Author: Greg Lutostanski
Author-email: greg.luto@gmail.com
License: UNKNOWN
Platform: UNKNOWN
Classifier: Programming Language :: Python :: 3.5
Requires-Dist: PyYAML
